{
  "batchbald_redux": {
    "Overview": "/",
    "BatchBALD Algorithm": "batchbald.html",
    "Joint Entropies": "joint_entropy_computation.html",
    "Consistent MC Dropout": "consistent_mc_dropout.html",
    "Active Learning": "active_learning.html",
    "FastMNIST": "fast_mnist.html",
    "Dataset Challenges": "dataset_challenges.html",
    "Datasets": "more_datasets.html",
    "Restoring Early Stopping": "restoring_early_stopping.html",
    "Thin wrapper to create models and optimizers": "model_optimizer_factory.html",
    "Some Models": "resnet_models.html",
    "Black Box Model Training": "black_box_training.html",
    "Trained Model Interface": "train_eval_model.html",
    "Semi-Supervised Learning": "SSL.html",
    "Experiment": "rejection_ood_experiment.html",
    "Results Visualizations": "X_arxiv_draft_report_plots.html",
    "Analysis of BALD scores during Training": "U_BALD_score_analysis.html",
    "Dependency Injection": "Z_dependency_injection.html"
  }
}